sbhelper/__init__.py
sbhelper/__main__.py
sbhelper/_constants.py
sbhelper/_database.py
sbhelper/_helper.py
sbhelper/_interface.py
sbhelper/_solver.py
sbhelper/_tools.py
sbhelper/command_line.py
sbhelper-0.21.dist-info/LICENSE
sbhelper-0.21.dist-info/METADATA
sbhelper-0.21.dist-info/WHEEL
sbhelper-0.21.dist-info/entry_points.txt
sbhelper-0.21.dist-info/top_level.txt
sbhelper-0.21.dist-info/RECORD
