Metadata-Version: 2.1
Name: sbhelper
Version: 0.21
Summary: CLI tool to help solve NYTimes Spelling Bee puzzles
Home-page: https://github.com/ctosullivan/Spelling-Bee-Helper
Author: Cormac O' Sullivan
Author-email: cormac@cosullivan.dev
License: MIT
Classifier: Programming Language :: Python :: 3
Classifier: License :: OSI Approved :: MIT License
Classifier: Operating System :: OS Independent
License-File: LICENSE
